main/__init__.py
main/__main__.py
clean_git_branches-1.0.3.2.dist-info/WHEEL
clean_git_branches-1.0.3.2.dist-info/entry_points.txt
clean_git_branches-1.0.3.2.dist-info/METADATA
clean_git_branches-1.0.3.2.dist-info/RECORD
