Metadata-Version: 2.1
Name: clean-git-branches
Version: 1.0.3.2
Summary: 
Keywords: git,branches,clean,delete,prune,local,remote
Author: Nick Holden
Author-email: holden.o.nick@gmail.com
Requires-Python: >=3.7,<4.0
Classifier: Programming Language :: Python :: 3
Classifier: Programming Language :: Python :: 3.7
Classifier: Programming Language :: Python :: 3.8
Classifier: Programming Language :: Python :: 3.9
Classifier: Programming Language :: Python :: 3.10
Classifier: Programming Language :: Python :: 3.11
Requires-Dist: GitPython (>=3.1.30,<4.0.0)
